README.md
setup.cfg
setup.py
src/hatsudenki/__init__.py
src/hatsudenki/manage.py
src/hatsudenki.egg-info/PKG-INFO
src/hatsudenki.egg-info/SOURCES.txt
src/hatsudenki.egg-info/dependency_links.txt
src/hatsudenki.egg-info/entry_points.txt
src/hatsudenki.egg-info/requires.txt
src/hatsudenki.egg-info/top_level.txt
src/hatsudenki/commands/__init__.py
src/hatsudenki/commands/base.py
src/hatsudenki/commands/build_master.py
src/hatsudenki/commands/generate.py
src/hatsudenki/commands/setup_dsl.py
src/hatsudenki/define/__init__.py
src/hatsudenki/define/config.py
src/hatsudenki/packages/__init__.py
src/hatsudenki/packages/batch.py
src/hatsudenki/packages/client.py
src/hatsudenki/packages/counter.py
src/hatsudenki/packages/cache/__init__.py
src/hatsudenki/packages/cache/base/__init__.py
src/hatsudenki/packages/cache/base/column.py
src/hatsudenki/packages/cache/base/define.py
src/hatsudenki/packages/cache/base/index.py
src/hatsudenki/packages/cache/base/memory/__init__.py
src/hatsudenki/packages/cache/base/memory/multi.py
src/hatsudenki/packages/cache/base/memory/solo.py
src/hatsudenki/packages/cache/base/memory/dynamic/__init__.py
src/hatsudenki/packages/cache/base/memory/dynamic/multi.py
src/hatsudenki/packages/cache/base/memory/dynamic/solo.py
src/hatsudenki/packages/cache/base/memory/dynamic/sync/__init__.py
src/hatsudenki/packages/cache/base/memory/dynamic/sync/multi.py
src/hatsudenki/packages/cache/base/memory/dynamic/sync/solo.py
src/hatsudenki/packages/cache/base/memory/static/__init__.py
src/hatsudenki/packages/cache/base/memory/static/multi.py
src/hatsudenki/packages/cache/base/memory/static/solo.py
src/hatsudenki/packages/cache/base/store/__init__.py
src/hatsudenki/packages/cache/base/store/inout.py
src/hatsudenki/packages/cache/base/store/table.py
src/hatsudenki/packages/cache/inmemory/__init__.py
src/hatsudenki/packages/cache/inmemory/manager.py
src/hatsudenki/packages/cache/inmemory/table.py
src/hatsudenki/packages/command/__init__.py
src/hatsudenki/packages/command/files.py
src/hatsudenki/packages/command/excel/__init__.py
src/hatsudenki/packages/command/excel/excel_data.py
src/hatsudenki/packages/command/hatsudenki/__init__.py
src/hatsudenki/packages/command/hatsudenki/data.py
