Metadata-Version: 1.0
Name: hatsudenki
Version: 0.0.1
Summary: "AWS DynamoDB ORM"
Home-page: https://github.com/Jumpei-Nakajima/hatsudenki
Author: jumpei-nakajima
Author-email: jumpei.nakajima@gmail.com
License: UNKNOWN
Platform: UNKNOWN
